climate_zarr/__init__.py
climate_zarr/_version.py
climate_zarr/calculate_county_stats.py
climate_zarr/climate_cli.py
climate_zarr/climate_config.py
climate_zarr/demo_cli.py
climate_zarr/py.typed
climate_zarr/stack_nc_to_zarr.py
climate_zarr-0.1.0.dist-info/licenses/LICENSE
climate_zarr-0.1.0.dist-info/METADATA
climate_zarr-0.1.0.dist-info/WHEEL
climate_zarr-0.1.0.dist-info/entry_points.txt
climate_zarr-0.1.0.dist-info/top_level.txt
climate_zarr-0.1.0.dist-info/RECORD
