Metadata-Version: 2.4
Name: climate-zarr
Version: 0.1.0
Summary: Interactive CLI toolkit for processing climate data with NetCDF to Zarr conversion and county-level analysis
Author-email: Chris Mihiar <chris.mihiar.fs@gmail.com>
License: MIT
Project-URL: Homepage, https://github.com/mihiarc/climate-zarr
Project-URL: Bug Tracker, https://github.com/mihiarc/climate-zarr/issues
Project-URL: Documentation, https://github.com/mihiarc/climate-zarr#readme
Keywords: climate,zarr,netcdf,data-processing,geospatial,science,county
Classifier: Development Status :: 4 - Beta
Classifier: Environment :: Console
Classifier: Intended Audience :: Science/Research
Classifier: License :: OSI Approved :: MIT License
Classifier: Operating System :: OS Independent
Classifier: Programming Language :: Python :: 3
Classifier: Programming Language :: Python :: 3.10
Classifier: Programming Language :: Python :: 3.11
Classifier: Programming Language :: Python :: 3.12
Classifier: Topic :: Scientific/Engineering :: Atmospheric Science
Classifier: Topic :: Scientific/Engineering :: GIS
Classifier: Topic :: Scientific/Engineering :: Information Analysis
Classifier: Topic :: Software Development :: Libraries :: Python Modules
Classifier: Typing :: Typed
Requires-Python: >=3.10
License-File: LICENSE
Requires-Dist: xarray>=2024.1.0
Requires-Dist: zarr>=2.16.0
Requires-Dist: netcdf4>=1.6.0
Requires-Dist: rich>=13.0.0
Requires-Dist: typer>=0.12.0
Requires-Dist: pydantic>=2.0.0
Requires-Dist: numpy>=1.24.0
Requires-Dist: dask[distributed]>=2024.1.0
Requires-Dist: pandas>=2.0.0
Requires-Dist: geopandas>=0.14.0
Requires-Dist: rioxarray>=0.15.0
Requires-Dist: shapely>=2.0.0
Requires-Dist: pyogrio>=0.9.0
Requires-Dist: virtualizarr>=1.0.0
Requires-Dist: h5py>=3.8.0
Requires-Dist: kerchunk>=0.2.5
Requires-Dist: fsspec>=2024.1.0
Requires-Dist: s3fs>=2024.1.0
Requires-Dist: intake>=0.7.0
Requires-Dist: xarray-datatree>=0.0.13
Requires-Dist: cf-xarray>=0.8.0
Requires-Dist: cftime>=1.6.0
Requires-Dist: bottleneck>=1.3.0
Requires-Dist: numcodecs>=0.12.0
Requires-Dist: questionary>=2.1.0
Provides-Extra: test
Requires-Dist: pytest>=7.4.0; extra == "test"
Requires-Dist: pytest-cov>=4.1.0; extra == "test"
Requires-Dist: pytest-xdist>=3.3.0; extra == "test"
Requires-Dist: pytest-mock>=3.11.0; extra == "test"
Provides-Extra: dev
Requires-Dist: ruff>=0.1.0; extra == "dev"
Requires-Dist: mypy>=1.5.0; extra == "dev"
Requires-Dist: pre-commit>=3.5.0; extra == "dev"
Dynamic: license-file
